flake8_pytest.py
flake8_pytest-1.4.dist-info/LICENSE
flake8_pytest-1.4.dist-info/METADATA
flake8_pytest-1.4.dist-info/WHEEL
flake8_pytest-1.4.dist-info/entry_points.txt
flake8_pytest-1.4.dist-info/top_level.txt
flake8_pytest-1.4.dist-info/RECORD
